ftimer/__init__.py
ftimer/main.py
ftimer-0.0.1.dist-info/METADATA
ftimer-0.0.1.dist-info/WHEEL
ftimer-0.0.1.dist-info/entry_points.txt
ftimer-0.0.1.dist-info/top_level.txt
ftimer-0.0.1.dist-info/RECORD
