Metadata-Version: 2.1
Name: ftimer
Version: 0.0.1
Summary: A freelancere timer to track your working time
Home-page: UNKNOWN
Author: Milad Khaleghi
Author-email: milad_khaleghi@live.com
License: UNKNOWN
Platform: UNKNOWN
